Metadata-Version: 2.2
Name: my_packet_aboba_nike_pro
Version: 0.0.1
Summary: Garik Harlamov
Author: Aboba nike pro
Author-email: dm.mishin06@gmail.com
Dynamic: author
Dynamic: author-email
Dynamic: summary
